flubar/__init__.py
flubar/bt.py
flubar/fe.py
flubar/vis.py
tests/__init__.py
tests/test_barcoding_testing.py
tests/test_feature_extraction.py
tests/test_visualization.py
flubar-1.0.dist-info/METADATA
flubar-1.0.dist-info/WHEEL
flubar-1.0.dist-info/entry_points.txt
flubar-1.0.dist-info/top_level.txt
flubar-1.0.dist-info/RECORD
